Aquar/BaseStrategy.py
Aquar/__init__.py
Aquar/subDataEngine/__init__.py
Aquar/subDataEngine/dataLoaderDaily.py
Aquar/utility/__init__.py
Aquar/utility/calc_utils.py
Aquar/utility/dataEngine.py
Aquar/utility/log.py
Aquar/utility/mysqlConnector.py
Aquar/utility/plotReturn.py
Aquar/utility/timeManager.py
Aquar/utility/utils.py
Aquar-1.0.6.dist-info/LICENSE.txt
Aquar-1.0.6.dist-info/METADATA
Aquar-1.0.6.dist-info/WHEEL
Aquar-1.0.6.dist-info/top_level.txt
Aquar-1.0.6.dist-info/RECORD
